sample_taggit/__init__.py
sample_taggit/admin.py
sample_taggit/asgi.py
sample_taggit/manage.py
sample_taggit/models.py
sample_taggit/settings.py
sample_taggit/urls.py
sample_taggit/views.py
sample_taggit/wsgi.py
sample_taggit/migrations/0001_initial.py
sample_taggit/migrations/__init__.py
taggit/__init__.py
taggit/admin.py
taggit/apps.py
taggit/forms.py
taggit/managers.py
taggit/models.py
taggit/serializers.py
taggit/utils.py
taggit/views.py
taggit/locale/ar/LC_MESSAGES/django.mo
taggit/locale/ar/LC_MESSAGES/django.po
taggit/locale/cs/LC_MESSAGES/django.mo
taggit/locale/cs/LC_MESSAGES/django.po
taggit/locale/da/LC_MESSAGES/django.mo
taggit/locale/da/LC_MESSAGES/django.po
taggit/locale/de/LC_MESSAGES/django.mo
taggit/locale/de/LC_MESSAGES/django.po
taggit/locale/el/LC_MESSAGES/django.mo
taggit/locale/el/LC_MESSAGES/django.po
taggit/locale/en/LC_MESSAGES/django.mo
taggit/locale/en/LC_MESSAGES/django.po
taggit/locale/eo/LC_MESSAGES/django.mo
taggit/locale/eo/LC_MESSAGES/django.po
taggit/locale/es/LC_MESSAGES/django.mo
taggit/locale/es/LC_MESSAGES/django.po
taggit/locale/fa/LC_MESSAGES/django.mo
taggit/locale/fa/LC_MESSAGES/django.po
taggit/locale/fi/LC_MESSAGES/django.mo
taggit/locale/fi/LC_MESSAGES/django.po
taggit/locale/fr/LC_MESSAGES/django.mo
taggit/locale/fr/LC_MESSAGES/django.po
taggit/locale/he/LC_MESSAGES/django.mo
taggit/locale/he/LC_MESSAGES/django.po
taggit/locale/it/LC_MESSAGES/django.mo
taggit/locale/it/LC_MESSAGES/django.po
taggit/locale/ja/LC_MESSAGES/django.mo
taggit/locale/ja/LC_MESSAGES/django.po
taggit/locale/nb/LC_MESSAGES/django.mo
taggit/locale/nb/LC_MESSAGES/django.po
taggit/locale/nl/LC_MESSAGES/django.mo
taggit/locale/nl/LC_MESSAGES/django.po
taggit/locale/pt_BR/LC_MESSAGES/django.mo
taggit/locale/pt_BR/LC_MESSAGES/django.po
taggit/locale/ru/LC_MESSAGES/django.mo
taggit/locale/ru/LC_MESSAGES/django.po
taggit/locale/tr/LC_MESSAGES/django.mo
taggit/locale/tr/LC_MESSAGES/django.po
taggit/locale/uk/LC_MESSAGES/django.mo
django_taggit-6.0.0.dist-info/AUTHORS
django_taggit-6.0.0.dist-info/LICENSE
django_taggit-6.0.0.dist-info/METADATA
django_taggit-6.0.0.dist-info/WHEEL
django_taggit-6.0.0.dist-info/top_level.txt
django_taggit-6.0.0.dist-info/RECORD
