Metadata-Version: 2.1
Name: django-taggit
Version: 6.0.0
Summary: django-taggit is a reusable Django application for simple tagging.
Home-page: https://github.com/jazzband/django-taggit
Author: Alex Gaynor
Author-email: alex.gaynor@gmail.com
License: BSD
Project-URL: Documentation, https://django-taggit.readthedocs.io
Project-URL: Source, https://github.com/jazzband/django-taggit
Project-URL: Tracker, https://github.com/jazzband/django-taggit/issues
Classifier: Development Status :: 5 - Production/Stable
Classifier: Environment :: Web Environment
Classifier: Framework :: Django
Classifier: Framework :: Django :: 4.1
Classifier: Framework :: Django :: 4.2
Classifier: Framework :: Django :: 5.0
Classifier: Intended Audience :: Developers
Classifier: License :: OSI Approved :: BSD License
Classifier: Operating System :: OS Independent
Classifier: Programming Language :: Python
Classifier: Programming Language :: Python :: 3
Classifier: Programming Language :: Python :: 3 :: Only
Classifier: Programming Language :: Python :: 3.8
Classifier: Programming Language :: Python :: 3.9
Classifier: Programming Language :: Python :: 3.10
Classifier: Programming Language :: Python :: 3.11
Classifier: Programming Language :: Python :: 3.12
Requires-Python: >=3.8
License-File: LICENSE
License-File: AUTHORS
Requires-Dist: Django>=4.1
